Metadata-Version: 2.1
Name: csv-trimming
Version: 1.1.1
Summary: Package python to remove common ugliness from a csv-like file
Home-page: https://github.com/LucaCappelletti94/csv_trimming
Author: LucaCappelletti94
Author-email: cappelletti.luca94@gmail.com
License: MIT
Classifier: Development Status :: 5 - Production/Stable
Classifier: License :: OSI Approved :: MIT License
Classifier: Programming Language :: Python :: 3
Requires-Python: >=3.9
Provides-Extra: test
License-File: LICENSE
